efftime/__init__.py
efftime/efftime.py
efftime-1.1.0.dist-info/LICENSE
efftime-1.1.0.dist-info/METADATA
efftime-1.1.0.dist-info/WHEEL
efftime-1.1.0.dist-info/top_level.txt
efftime-1.1.0.dist-info/RECORD
