Metadata-Version: 2.1
Name: efftime
Version: 1.1.0
Summary: A check Program run efficiency.
Author: BreezeSun
License: MIT
License-File: LICENSE
